{"avgSubsPerMatch":[{"team":"K. VC Ardooie A","matches":23,"subs":99,"avgSubs":4.3},{"team":"K. FC Marke A","matches":23,"subs":89,"avgSubs":3.87},{"team":"K. SV Moorsele A","matches":22,"subs":80,"avgSubs":3.64},{"team":"K. RC Bissegem","matches":23,"subs":83,"avgSubs":3.61},{"team":"K.R.C. Waregem A","matches":22,"subs":79,"avgSubs":3.59},{"team":"K. WS Oudenburg","matches":23,"subs":82,"avgSubs":3.57},{"team":"KFC Aalbeke Sport A","matches":22,"subs":78,"avgSubs":3.55},{"team":"K. FC Heist A","matches":23,"subs":78,"avgSubs":3.39},{"team":"S.V. Wevelgem City A","matches":23,"subs":75,"avgSubs":3.26},{"team":"Club Roeselare","matches":23,"subs":74,"avgSubs":3.22},{"team":"K.S.C. Wielsbeke","matches":22,"subs":70,"avgSubs":3.18},{"team":"FC Sp. Heestert A","matches":23,"subs":70,"avgSubs":3.04},{"team":"Zwevegem Sport","matches":23,"subs":66,"avgSubs":2.87},{"team":"K. SV Bredene A","matches":23,"subs":64,"avgSubs":2.78},{"team":"K. Eendr. Wervik A","matches":23,"subs":61,"avgSubs":2.65},{"team":"K. FC Varsenare A","matches":23,"subs":57,"avgSubs":2.48}],"goalDiffAfterSub":[{"team":"K. SV Bredene A","gd10":-0.45,"gd20":-0.8,"standard10":-0.58,"standard20":-1.16,"delta10":0.13,"delta20":0.36},{"team":"Zwevegem Sport","gd10":0.17,"gd20":0.41,"standard10":0.11,"standard20":0.22,"delta10":0.06,"delta20":0.19},{"team":"K. VC Ardooie A","gd10":0.05,"gd20":0.19,"standard10":0.04,"standard20":0.08,"delta10":0.01,"delta20":0.11},{"team":"K. WS Oudenburg","gd10":-0.12,"gd20":-0.04,"standard10":-0.06,"standard20":-0.12,"delta10":-0.06,"delta20":0.08},{"team":"K. Eendr. Wervik A","gd10":0.16,"gd20":0.26,"standard10":0.1,"standard20":0.2,"delta10":0.06,"delta20":0.06},{"team":"K. RC Bissegem","gd10":0.07,"gd20":0.12,"standard10":0.03,"standard20":0.07,"delta10":0.04,"delta20":0.05},{"team":"K.R.C. Waregem A","gd10":0.09,"gd20":0.15,"standard10":0.07,"standard20":0.14,"delta10":0.02,"delta20":0.01},{"team":"K. SV Moorsele A","gd10":-0.09,"gd20":-0.21,"standard10":-0.1,"standard20":-0.19,"delta10":0.01,"delta20":-0.02},{"team":"S.V. Wevelgem City A","gd10":0.08,"gd20":0.17,"standard10":0.1,"standard20":0.2,"delta10":-0.02,"delta20":-0.03},{"team":"K. FC Marke A","gd10":0.0,"gd20":0.08,"standard10":0.06,"standard20":0.13,"delta10":-0.06,"delta20":-0.05},{"team":"K.S.C. Wielsbeke","gd10":0.07,"gd20":0.2,"standard10":0.13,"standard20":0.25,"delta10":-0.06,"delta20":-0.05},{"team":"K. FC Varsenare A","gd10":-0.02,"gd20":0.05,"standard10":0.06,"standard20":0.13,"delta10":-0.08,"delta20":-0.08},{"team":"FC Sp. Heestert A","gd10":-0.03,"gd20":-0.09,"standard10":0.0,"standard20":0.0,"delta10":-0.03,"delta20":-0.09},{"team":"K. FC Heist A","gd10":-0.05,"gd20":-0.08,"standard10":0.0,"standard20":0.01,"delta10":-0.05,"delta20":-0.09},{"team":"KFC Aalbeke Sport A","gd10":-0.06,"gd20":-0.09,"standard10":0.03,"standard20":0.05,"delta10":-0.09,"delta20":-0.14},{"team":"Club Roeselare","gd10":-0.09,"gd20":-0.15,"standard10":0.0,"standard20":0.0,"delta10":-0.09,"delta20":-0.15}],"leagueTiming":{"buckets":{"0-60":255,"61-75":474,"76-90":476},"totalSubs":1205},"timingByTeam":{"Club Roeselare":[{"bucket":"0-60 min","count":13,"pct":17.6,"leaguePct":21.2},{"bucket":"61-75 min","count":24,"pct":32.4,"leaguePct":39.3},{"bucket":"76-90 min","count":37,"pct":50.0,"leaguePct":39.5}],"FC Sp. Heestert A":[{"bucket":"0-60 min","count":20,"pct":28.6,"leaguePct":21.2},{"bucket":"61-75 min","count":20,"pct":28.6,"leaguePct":39.3},{"bucket":"76-90 min","count":30,"pct":42.9,"leaguePct":39.5}],"K. Eendr. Wervik A":[{"bucket":"0-60 min","count":13,"pct":21.3,"leaguePct":21.2},{"bucket":"61-75 min","count":22,"pct":36.1,"leaguePct":39.3},{"bucket":"76-90 min","count":26,"pct":42.6,"leaguePct":39.5}],"K. FC Heist A":[{"bucket":"0-60 min","count":15,"pct":19.2,"leaguePct":21.2},{"bucket":"61-75 min","count":35,"pct":44.9,"leaguePct":39.3},{"bucket":"76-90 min","count":28,"pct":35.9,"leaguePct":39.5}],"K. FC Marke A":[{"bucket":"0-60 min","count":17,"pct":19.1,"leaguePct":21.2},{"bucket":"61-75 min","count":36,"pct":40.4,"leaguePct":39.3},{"bucket":"76-90 min","count":36,"pct":40.4,"leaguePct":39.5}],"K. FC Varsenare A":[{"bucket":"0-60 min","count":9,"pct":15.8,"leaguePct":21.2},{"bucket":"61-75 min","count":19,"pct":33.3,"leaguePct":39.3},{"bucket":"76-90 min","count":29,"pct":50.9,"leaguePct":39.5}],"K. RC Bissegem":[{"bucket":"0-60 min","count":15,"pct":18.1,"leaguePct":21.2},{"bucket":"61-75 min","count":31,"pct":37.3,"leaguePct":39.3},{"bucket":"76-90 min","count":37,"pct":44.6,"leaguePct":39.5}],"K. SV Bredene A":[{"bucket":"0-60 min","count":18,"pct":28.1,"leaguePct":21.2},{"bucket":"61-75 min","count":34,"pct":53.1,"leaguePct":39.3},{"bucket":"76-90 min","count":12,"pct":18.8,"leaguePct":39.5}],"K. SV Moorsele A":[{"bucket":"0-60 min","count":28,"pct":35.0,"leaguePct":21.2},{"bucket":"61-75 min","count":32,"pct":40.0,"leaguePct":39.3},{"bucket":"76-90 min","count":20,"pct":25.0,"leaguePct":39.5}],"K. VC Ardooie A":[{"bucket":"0-60 min","count":17,"pct":17.2,"leaguePct":21.2},{"bucket":"61-75 min","count":35,"pct":35.4,"leaguePct":39.3},{"bucket":"76-90 min","count":47,"pct":47.5,"leaguePct":39.5}],"K. WS Oudenburg":[{"bucket":"0-60 min","count":13,"pct":15.9,"leaguePct":21.2},{"bucket":"61-75 min","count":38,"pct":46.3,"leaguePct":39.3},{"bucket":"76-90 min","count":31,"pct":37.8,"leaguePct":39.5}],"K.R.C. Waregem A":[{"bucket":"0-60 min","count":17,"pct":21.5,"leaguePct":21.2},{"bucket":"61-75 min","count":37,"pct":46.8,"leaguePct":39.3},{"bucket":"76-90 min","count":25,"pct":31.6,"leaguePct":39.5}],"K.S.C. Wielsbeke":[{"bucket":"0-60 min","count":10,"pct":14.3,"leaguePct":21.2},{"bucket":"61-75 min","count":26,"pct":37.1,"leaguePct":39.3},{"bucket":"76-90 min","count":34,"pct":48.6,"leaguePct":39.5}],"KFC Aalbeke Sport A":[{"bucket":"0-60 min","count":21,"pct":26.9,"leaguePct":21.2},{"bucket":"61-75 min","count":35,"pct":44.9,"leaguePct":39.3},{"bucket":"76-90 min","count":22,"pct":28.2,"leaguePct":39.5}],"S.V. Wevelgem City A":[{"bucket":"0-60 min","count":15,"pct":20.0,"leaguePct":21.2},{"bucket":"61-75 min","count":19,"pct":25.3,"leaguePct":39.3},{"bucket":"76-90 min","count":41,"pct":54.7,"leaguePct":39.5}],"Zwevegem Sport":[{"bucket":"0-60 min","count":14,"pct":21.2,"leaguePct":21.2},{"bucket":"61-75 min","count":31,"pct":47.0,"leaguePct":39.3},{"bucket":"76-90 min","count":21,"pct":31.8,"leaguePct":39.5}]}}